KataRangePack/__init__.py
KataRangesPack-0.1.dist-info/LICENCE.txt
KataRangesPack-0.1.dist-info/METADATA
KataRangesPack-0.1.dist-info/WHEEL
KataRangesPack-0.1.dist-info/top_level.txt
KataRangesPack-0.1.dist-info/RECORD
