Metadata-Version: 2.1
Name: KataRangesPack
Version: 0.1
Summary: <Basic desc>
Home-page: UNKNOWN
Author: Deivy & Jordi
Author-email: 1099429@est.intec.edu.do
License: UNKNOWN
Platform: UNKNOWN
Classifier: Programming Language :: Python :: 3
Classifier: License :: OSI Approved :: MIT License
Classifier: Operating System :: OS Independent
License-File: LICENCE.txt
